marionette_transport/__init__.py
marionette_transport/transport.py
marionette_transport-1.2.0.dist-info/DESCRIPTION.rst
marionette_transport-1.2.0.dist-info/METADATA
marionette_transport-1.2.0.dist-info/RECORD
marionette_transport-1.2.0.dist-info/WHEEL
marionette_transport-1.2.0.dist-info/entry_points.txt
marionette_transport-1.2.0.dist-info/metadata.json
marionette_transport-1.2.0.dist-info/top_level.txt
