Metadata-Version: 2.0
Name: marionette-transport
Version: 1.2.0
Summary: Transport layer for Marionette client
Home-page: https://developer.mozilla.org/en-US/docs/Marionette
Author: Mozilla Automation and Tools Team
Author-email: tools@lists.mozilla.org
License: MPL
Keywords: mozilla
Platform: UNKNOWN
